checkarg/__init__.py
checkarg/list.py
checkarg/none_type.py
checkarg/number.py
checkarg/text.py
checkarg/exceptions/__init__.py
checkarg/exceptions/error_messages.py
checkarg/exceptions/exceptions.py
checkarg-0.2.0.dist-info/LICENSE
checkarg-0.2.0.dist-info/METADATA
checkarg-0.2.0.dist-info/WHEEL
checkarg-0.2.0.dist-info/top_level.txt
checkarg-0.2.0.dist-info/RECORD
