Metadata-Version: 2.1
Name: checkarg
Version: 0.2.0
Summary: Guard clause library for Python projects, to validate arguments on every python function/method.
Home-page: https://github.com/Farfetch/checkarg.git
Author: farfetch
Author-email: opensource@farfetch.com
License: MIT License (MIT)
Platform: UNKNOWN
License-File: LICENSE
